{
    "issue":  "QUA-95",
    "generated_at_local":  "2026-04-27T12:23:14+02:00",
    "refresh_executed":  false,
    "refresh_exit_code":  null,
    "audit_executed":  false,
    "audit_exit_code":  null,
    "gate":  {
                 "recommended_state":  "blocked",
                 "reason":  "acceptance_not_met",
                 "disposition":  "defer",
                 "bars_got":  0,
                 "tail_shortfall_seconds":  7141.322,
                 "last_checked_local":  "2026-04-27T12:22:43+02:00"
             },
    "infra_audit":  {
                        "overall_status":  "critical",
                        "checks_count":  22,
                        "issues_count":  2
                    }
}
